CHPCDIANA/DIANA.py
CHPCDIANA/__init__.py
CHPCDIANA-0.0.9.dist-info/LICENSE.txt
CHPCDIANA-0.0.9.dist-info/METADATA
CHPCDIANA-0.0.9.dist-info/WHEEL
CHPCDIANA-0.0.9.dist-info/top_level.txt
CHPCDIANA-0.0.9.dist-info/RECORD
