Metadata-Version: 2.1
Name: CHPCDIANA
Version: 0.0.9
Summary: Implementation of the Divisive Analysis algorithm for clustering.
Home-page: 
Author: Ismail EL Yamani, Salma EL Omari, Widad EL Moutaouakal, Youssef EL Mrabet
Author-email: ismail.elyamani.2000@gmail.com
License: MIT
Keywords: Divisive Analysis
Platform: UNKNOWN
Classifier: Development Status :: 5 - Production/Stable
Classifier: Intended Audience :: Science/Research
Classifier: Operating System :: Microsoft :: Windows :: Windows 10
Classifier: License :: OSI Approved :: MIT License
Classifier: Programming Language :: Python :: 3
License-File: LICENSE.txt
